{"links": [{"source": 2, "name": "is_a", "target": 1}, {"source": 2, "name": "is_a", "target": 3}, {"source": 2, "name": "alias", "target": 0}, {"source": 9, "name": "alias", "target": 4}, {"source": 9, "name": "alias", "target": 5}, {"source": 6, "name": "and", "target": 7}, {"source": 6, "name": "and", "target": 8}, {"source": 7, "name": "and", "target": 8}, {"source": 9, "name": "subset_where", "target": 10}, {"source": 9, "name": "subset_where", "target": 11}, {"source": 10, "name": "subset_where", "target": 11}, {"source": 12, "name": "subset_where", "target": 13}, {"source": 12, "name": "subset_where", "target": 14}, {"source": 13, "name": "subset_where", "target": 14}, {"source": 18, "name": "more", "target": 20}, {"source": 15, "name": "causes", "target": 17}, {"source": 16, "name": "causes", "target": 17}, {"source": 19, "name": "causes", "target": 20}, {"source": 20, "name": "causes", "target": 21}, {"source": 22, "name": "plus", "target": 23}, {"source": 22, "name": "plus", "target": 29}, {"source": 23, "name": "plus", "target": 29}, {"source": 22, "name": "plus", "target": 23}, {"source": 29, "name": "plus", "target": 24}, {"source": 25, "name": "multiply", "target": 26}, {"source": 27, "name": "divide", "target": 28}, {"source": 29, "name": "equals", "target": 30}], "nodes": [{"name": "jon blow"}, {"name": "person"}, {"name": "jonathan blow"}, {"name": "fucking baller-ass"}, {"name": "b"}, {"name": "c"}, {"name": "x"}, {"name": "y"}, {"name": "z"}, {"name": "a"}, {"name": "(x . y . z)"}, {"name": "(1 + 2 + 3)"}, {"name": "circle"}, {"name": "n-sphere"}, {"name": "n=1"}, {"name": "calm brow"}, {"name": "tilt head"}, {"name": "\u03b5\u03c5"}, {"name": "ACh"}, {"name": "piracetam"}, {"name": "+ ACh"}, {"name": "smarter"}, {"name": "1"}, {"name": "2"}, {"name": "4"}, {"name": "(1 + 2)"}, {"name": "(3 + 4)"}, {"name": "((1 + 2) * (3 + 4))"}, {"name": "7"}, {"name": "3"}, {"name": "(((1 + 2) * (3 + 4)) / 7)"}]}
